flask_sso_ui/__init__.py
flask_sso_ui/additional-info.json
flask_sso_ui/decorators.py
flask_sso_ui/utils.py
flask_sso_ui-0.1.2.dist-info/LICENSE
flask_sso_ui-0.1.2.dist-info/METADATA
flask_sso_ui-0.1.2.dist-info/WHEEL
flask_sso_ui-0.1.2.dist-info/top_level.txt
flask_sso_ui-0.1.2.dist-info/RECORD
