Metadata-Version: 2.1
Name: flask-sso-ui
Version: 0.1.2
Summary: A simple SSO UI CAS wrapper for Flask
Home-page: https://github.com/DhanarSantika/flask-sso-ui
Author: Made Wira Dhanar Santika
Author-email: dhanar.santika@gmail.com
License: MIT
Platform: UNKNOWN
Classifier: Programming Language :: Python :: 3
Classifier: Programming Language :: Python :: 3.6
Classifier: License :: OSI Approved :: MIT License
Requires-Dist: python-cas
Requires-Dist: flask
Requires-Dist: requests
